{
  "name": "股票新闻监控列表",
  "description": "每个交易日晚上21点检索这些股票的重要新闻和公告",
  "stocks": [
    {"code": "688256", "name": "寒武纪", "weight": "13.36%"},
    {"code": "688008", "name": "澜起科技", "weight": "9.40%"},
    {"code": "688981", "name": "中芯国际", "weight": "9.08%"},
    {"code": "688041", "name": "海光信息", "weight": "8.87%"},
    {"code": "688012", "name": "中微公司", "weight": "6.31%"},
    {"code": "688525", "name": "佰维存储", "weight": "3.88%"},
    {"code": "688072", "name": "拓荆科技", "weight": "3.84%"},
    {"code": "688521", "name": "芯原股份", "weight": "3.30%"},
    {"code": "688120", "name": "华海清科", "weight": "2.35%"},
    {"code": "688271", "name": "联影医疗", "weight": "2.16%"}
  ],
  "createdAt": "2026-03-18",
  "updatedAt": "2026-05-31",
  "note": "科创50指数(000688)前十大权重股，权重日期2026-05-29"
}
